[
    {
        "question_number": "1",
        "question_type": "单选题",
        "question_text": "2008年12月，中央召开经济工作会 议，强调科学发展观第一要义是( )，越是在经济 发展面临较大困难的时候，我们越是要坚定不移 地贯彻皮展是硬道理的战略思想。",
        "options": {
            "A": "开放",
            "B": "上友展",
            "C": "改革",
            "D": "以人为本"
        },
        "correct_answer": "B",
        "error_count": 0,
        "correct_count": 0
    },
    {
        "question_number": "2",
        "question_type": "单选题",
        "question_text": "1956年，随着苏共二十大的召开和波 匈加件的发生，( )的浆端初步暴露出来。",
        "options": {
            "A": "人民公社化",
            "B": "苏联模式",
            "C": "社会主义",
            "D": "大跃进"
        },
        "correct_answer": "B",
        "error_count": 0,
        "correct_count": 0
    },
    {
        "question_number": "3",
        "question_type": "单选题",
        "question_text": "2017年，党的( )把习近平新时代中国 特色社会主义思想确立为党必须长期坚持的指导 思想并庄严地写入党章，实现了党的指导思想的 与时俱进。",
        "options": {
            "A": "十七大",
            "B": "十九大",
            "C": "十八大",
            "D": "二十大"
        },
        "correct_answer": "B",
        "error_count": 0,
        "correct_count": 0
    },
    {
        "question_number": "4",
        "question_type": "单选题",
        "question_text": "我国改革从( )率先突破，逐步转向城 市经济体制改革并全面铺开，确立社会主义市场 经济的改革方向。",
        "options": {
            "A": "包干到户",
            "B": "计划少一点，市场多一点",
            "C": "农村实行家庭联产承包责任制",
            "D": "计划经济为主，市场经济为辅"
        },
        "correct_answer": "C",
        "error_count": 0,
        "correct_count": 0
    },
    {
        "question_number": "5",
        "question_type": "单选题",
        "question_text": "( )的响法修正案正式将邓小平理论载 入完法。",
        "options": {
            "A": "1998年",
            "B": "1999年",
            "C": "2001年",
            "D": "2000年"
        },
        "correct_answer": "B",
        "error_count": 0,
        "correct_count": 0
    },
    {
        "question_number": "6",
        "question_type": "单选题",
        "question_text": "南方谈话是( )的集大成之作，从理论 上深刻地回答了当时困扰和束缚人们思想的一系 列重大问题，推动改革开放和社会主义现代化建 设进入新阶段，邓小平理论也逐步走向成熟。",
        "options": {
            "A": "毛泽东思想",
            "B": "“三个代表\"重要思想",
            "C": "科学发展观",
            "D": "邓小平理论"
        },
        "correct_answer": "D",
        "error_count": 0,
        "correct_count": 0
    },
    {
        "question_number": "7",
        "question_type": "单选题",
        "question_text": "2002年11月，党的（）将“三个代表”重要思想同马克思列宁主义、毛泽东思想和邓小平理论一道确立为党必须长期坚持的指导思想，并写入党章，实现了我们党指导思想的又一次与时俱进。",
        "options": {
            "A": "十六大",
            "B": "十八大",
            "C": "十七大",
            "D": "十五大"
        },
        "correct_answer": "A",
        "error_count": 0,
        "correct_count": 0
    },
    {
        "question_number": "8",
        "question_type": "单选题",
        "question_text": "以胡锦涛同志为主要代表的中国共产 党人，创造性地回答了( )这一重大问题。",
        "options": {
            "A": "什么是社会主义，怎样建设社会主义",
            "B": "实现什么样的发展、怎样发展",
            "C": "建设什么样的党，怎样建设党",
            "D": "什么是马克思主义，怎样必展马克思主义"
        },
        "correct_answer": "B",
        "error_count": 0,
        "correct_count": 0
    },
    {
        "question_number": "9",
        "question_type": "单选题",
        "question_text": "我们党的文件中第一次提出科学发展 观是在()。",
        "options": {
            "A": "党的十七大",
            "B": "党的十六大",
            "C": "党的十六届三中全会",
            "D": "党的十六届四中全会"
        },
        "correct_answer": "C",
        "error_count": 0,
        "correct_count": 0
    },
    {
        "question_number": "10",
        "question_type": "单选题",
        "question_text": "1978年12月召开的党的十一届三中全 会，重新确立了( )的思想路线，彻底否定了 以阶 级斗争为纲 的错误理论和实践。",
        "options": {
            "A": "群众路线",
            "B": "独立自主",
            "C": "实事求是",
            "D": "解放思想"
        },
        "correct_answer": "C",
        "error_count": 0,
        "correct_count": 0
    },
    {
        "question_number": "11",
        "question_type": "单选题",
        "question_text": "党的( )把科学发展观写入党章，科学 发展观进一步走向成熟。",
        "options": {
            "A": "十八大",
            "B": "十九大",
            "C": "十七大",
            "D": "十六大"
        },
        "correct_answer": "C",
        "error_count": 0,
        "correct_count": 0
    },
    {
        "question_number": "12",
        "question_type": "单选题",
        "question_text": "党的十一届三中全会以后，以( )同志 为主要代表的中国共声让人 领导全党和全国人 民果断地纠正了这些错误，深刻地分析了错误 现的原因，同时又坚决地维护和继承了过去在理 论上和实践上所取得的一切积极成果。",
        "options": {
            "A": "陈云",
            "B": "胡耀邦",
            "C": "叶剑英",
            "D": "邓小平"
        },
        "correct_answer": "D",
        "error_count": 0,
        "correct_count": 0
    },
    {
        "question_number": "13",
        "question_type": "单选题",
        "question_text": "2018年，( )通过的完法修正案，郑重 地把习近平新时代中国特色社会主义思想载入宪 法，实现了国家指导思想的与时俱进。",
        "options": {
            "A": "十四届全国人大二次会议",
            "B": "十三届全国人大一",
            "C": "十四届全国人大一次会议",
            "D": "十三届全国人大二次会议"
        },
        "correct_answer": "B",
        "error_count": 0,
        "correct_count": 0
    },
    {
        "question_number": "14",
        "question_type": "单选题",
        "question_text": "首次对“三个代表\"进行了比较全面的 阐述是:()",
        "options": {
            "A": "2000年，江泽民在广东考察工作时",
            "B": "1997年党十五大",
            "C": "1989年党十四届三中全会",
            "D": "2001年7月1日，江泽民在庆祝中国共产党成立"
        },
        "correct_answer": "A",
        "error_count": 0,
        "correct_count": 0
    },
    {
        "question_number": "15",
        "question_type": "单选题",
        "question_text": "1997年召开的党的( )正式提出 邓小 平理论 这一概念，深刻前述了邓小平理论的历史 地位和指导意义，进一步论述了邓小平对这一理 论的创立作出的独创性贡献。",
        "options": {
            "A": "十五大",
            "B": "十六大",
            "C": "十七大",
            "D": "十四大"
        },
        "correct_answer": "A",
        "error_count": 0,
        "correct_count": 0
    },
    {
        "question_number": "16",
        "question_type": "单选题",
        "question_text": "党的十四大指出，我们党所以能够取 得这样的胜利，根本原因是在十四年的伟大实践 中，坚持把( )同中国具体实际相结合，逐步形成 和发展了建设有中国特色社会主义的理论。",
        "options": {
            "A": "科学社会主义",
            "B": "毛泽东思想",
            "C": "列宁主义",
            "D": "马克思主义基本原理"
        },
        "correct_answer": "D",
        "error_count": 0,
        "correct_count": 0
    },
    {
        "question_number": "17",
        "question_type": "单选题",
        "question_text": "1987年召开的党的十三大，第一次比较系统地论述了我国社会主义初级阶段理论，明确概括和全面阐发了党的（）的基本路线。",
        "options": {
            "A": "“一个中心、两个基本点”",
            "B": "社会主义全面发展",
            "C": "“四项基本原则",
            "D": "“三步走”"
        },
        "correct_answer": "A",
        "error_count": 0,
        "correct_count": 0
    },
    {
        "question_number": "18",
        "question_type": "单选题",
        "question_text": "科技进步日新月异，以( )为核心的高 新技术的发展，极大地改变了人们的生产、生活 方式和国际经济、政治关系。",
        "options": {
            "A": "经济革命",
            "B": "多极化",
            "C": "全球化",
            "D": "信息技术"
        },
        "correct_answer": "D",
        "error_count": 0,
        "correct_count": 0
    },
    {
        "question_number": "19",
        "question_type": "单选题",
        "question_text": "1982年邓小平在党的十二大开幕词中 明确提出:走自己的道路，( )。",
        "options": {
            "A": "建设社会主义初级阶段",
            "B": "建设社会主义市场经济",
            "C": "实现马克思主义中国化时代化",
            "D": "建设有中国特色的社会主义"
        },
        "correct_answer": "D",
        "error_count": 0,
        "correct_count": 0
    },
    {
        "question_number": "20",
        "question_type": "多选题",
        "question_text": "我国在社会主义建设初期走了不少碍 路、犯了不少错误，其深层原因是:( )",
        "options": {
            "A": "经济上急于求成、盲目求纯和急于过渡",
            "B": "对什么是社会主义和如何建设社会主义的问题",
            "C": "偏离了党的实事求是的思想路线",
            "D": "在政治上坚持以阶级斗争为网"
        },
        "correct_answer": "BC",
        "error_count": 0,
        "correct_count": 0
    },
    {
        "question_number": "21",
        "question_type": "多选题",
        "question_text": "2004年3月，胡锦涛在中央人口资源 环境座谈会上发表重要讲话，深刻前明了科学上 展观提出的背景、意义，明确界定了( )的深刻内 涵和基本要求，并对如何树立和落实科学发展观 提出了明确的要求，标志着科学发展观的形成。",
        "options": {
            "A": "协调发展",
            "B": "全面皮展",
            "C": "可持续发展",
            "D": "以人为本"
        },
        "correct_answer": "ABCD",
        "error_count": 0,
        "correct_count": 0
    },
    {
        "question_number": "22",
        "question_type": "多选题",
        "question_text": "党的十八大以来，中国特色社会主义 进入新时代，这是我国发展新的历史方位。这个 中国特色社会主义新时代是指( )。",
        "options": {
            "A": "全国各族人民团结奋斗、不断创造美好生活、",
            "B": "承前启后、继往开来、在新的历史条件下继续",
            "C": "决胜全面建成小康社会、进而全面建设社会主",
            "D": "全体中华儿女勤力同心、奋力实现中华民族伟"
        },
        "correct_answer": "ABCD",
        "error_count": 0,
        "correct_count": 0
    },
    {
        "question_number": "23",
        "question_type": "多选题",
        "question_text": "新世纪新阶段，经济社会发展呈现一 系列新的阶段性特征，主要表现有( )。",
        "options": {
            "A": "国际竞争日趋激烈，风险与考验增多",
            "B": "自主创新能力不强，经济友展粗放",
            "C": "城乡、区域协调发展任务艰巨",
            "D": "收入差距拉大尚未根本扭转"
        },
        "correct_answer": "ABCD",
        "error_count": 0,
        "correct_count": 0
    },
    {
        "question_number": "24",
        "question_type": "多选题",
        "question_text": "中国特色社会主义理论体系是中国共 产党长期探索的伟大理论创造，同( )一脉相承又 与时俱进，是马克思主义中国化时代化的重大理 论成果。",
        "options": {
            "A": "邓小平理论",
            "B": "毛泽东思想",
            "C": "马克思列宁主义",
            "D": "空想社会主义",
        },
        "correct_answer": "BC",
        "error_count": 0,
        "correct_count": 0
    },
    {
        "question_number": "25",
        "question_type": "多选题",
        "question_text": "2002年5月，江泽民在中共中央党校 省部级干部进修班毕业典礼上深刻阐述了 三个代 表 重要思想的内在联系，提出 贯彻 三个代表 重 要思想，( )。",
        "options": {
            "A": "目标在坚持联系群众",
            "B": "关键在坚持与时俱进",
            "C": "核心在坚持党的先进性",
            "D": "本质在坚持执政为民"
        },
        "correct_answer": "BCD",
        "error_count": 0,
        "correct_count": 0
    },
    {
        "question_number": "26",
        "question_type": "多选题",
        "question_text": "胡锦涛在纪念中国共产党十一届三中全会召开30周年大会中系统阐述了中国在改革开放实践中积累的宝贵经验，概括而言就是“十个结合”，以下哪些属于“十个结合”的宝贵经验的是（)。",
        "options": {
            "A": "把坚持社会主义基本制度同发展市场经济结合起来",
            "B": "把发展社会生产力同提高全民族文明素质结合起来",
            "C": "把坚持马克思主义基本原理同推进马克思主义中国化结合起来",
            "D": "把坚持独立自主同参与经济全球化结合起来"
        },
        "correct_answer": "ABCD",
        "error_count": 0,
        "correct_count": 0
    },
    {
        "question_number": "27",
        "question_type": "多选题",
        "question_text": "习近平新时代中国特色社会主义思想 是( )。",
        "options": {
            "A": "当代中国马克思主义",
            "B": "创新的马克思主义",
            "C": "21世纪马克思主义",
            "D": "永远的马克思主义"
        },
        "correct_answer": "ACD",
        "error_count": 0,
        "correct_count": 0
    },
    {
        "question_number": "28",
        "question_type": "多选题",
        "question_text": "习近平新时代中国特色社会主义思想 科学回答了( )等重大时代课题。",
        "options": {
            "A": "新时代坚持和发展什么样的中国特色社会主",
            "B": "实现什么样的人类发展、怎样实现人类发展",
            "C": "建设什么样的社会主义现代化强国、怎样建设",
            "D": "建设什么样的长期执政的马克思主义政党、怎"
        },
        "correct_answer": "ACD",
        "error_count": 0,
        "correct_count": 0
    },
    {
        "question_number": "29",
        "question_type": "多选题",
        "question_text": "党的十八大以来，( )正以前所未有的 方式展开，世界百年未有之大变局加速演进。",
        "options": {
            "A": "历史之变",
            "B": "世界之变",
            "C": "时代之变",
            "D": "人类之变"
        },
        "correct_answer": "ABC",
        "error_count": 0,
        "correct_count": 0
    },
    {
        "question_number": "30",
        "question_type": "多选题",
        "question_text": "以习近平同志为核心的党中央以伟大 的历史主动精神、巨大的政治勇气、强烈的责任 担当，统筹国内国际两个大局，统揽( )，创立习 近平新时代中国特色社会主义思想，明确坚持和 发展中国特色社会主义的基本方略，提出一系列 治国理政新理念新思想新战略，实现了马克思主 义中国化时代化新的飞跃。",
        "options": {
            "A": "伟大事业",
            "B": "伟大工程",
            "C": "伟大斗争",
            "D": "伟大梦想"
        },
        "correct_answer": "ABCD",
        "error_count": 0,
        "correct_count": 0
    },
    {
        "question_number": "31",
        "question_type": "多选题",
        "question_text": "中国特色社会主义进入新时代，意味 着中国特色社会主义( )不断发展，拓展了发展中 国家走向现代化的途径，给世界上那些既希望加 快发展又希望保持自身独立性的国家和民族提供 了全新选择，为解决人类问题贡献了中国智慧和 中国方案。",
        "options": {
            "A": "文化",
            "B": "制度",
            "C": "理论",
            "D": "道路"
        },
        "correct_answer": "ABCD",
        "error_count": 0,
        "correct_count": 0
    },
    {
        "question_number": "32",
        "question_type": "多选题",
        "question_text": "1989-2002年，国际局势的深刻变动 对引领中国改革发展的中国共产党形成前所未有 的压力和考验，所面临的国际局势有哪些( )。",
        "options": {
            "A": "霸权主义抬头",
            "B": "经济全球化纵深推进",
            "C": "苏东剧变",
            "D": "新科技革命迅猛发展"
        },
        "correct_answer": "ABCD",
        "error_count": 0,
        "correct_count": 0
    },
    {
        "question_number": "33",
        "question_type": "多选题",
        "question_text": "新世纪新阶段，我国进入( )，经济社 会发展呈现一系列新的阶段性特征。",
        "options": {
            "A": "改革攻坚期",
            "B": "矛盾凸显期",
            "C": "发展关键期",
            "D": "开放活跃期"
        },
        "correct_answer": "ABC",
        "error_count": 0,
        "correct_count": 0
    },
    {
        "question_number": "34",
        "question_type": "多选题",
        "question_text": "习近平新时代中国特色社会主义思想 内涵十分丰富，党的十九大、十九届六中全会提 出的( )概括了习近平新时代中国特色社会主义思 想的主要内容。 A，十三个方面成就 B，两步走 战略安排 C，十四个坚持- D，十个明确”",
        "options": {
            "A": "十三个方面成就",
            "B": "两步走战略安排",
            "C": "十四个坚持",
            "D": "十个明确"
        },
        "correct_answer": "ACD",
        "error_count": 0,
        "correct_count": 0
    },
    {
        "question_number": "35",
        "question_type": "多选题",
        "question_text": "以习近平同志为核心的党中央统筹把 最) 坚持把马克思主义基本原理同中国具体实 际相结合、同中华优秀传统文化相结合。",
        "options": {
            "A": "国家安全",
            "B": "改革开放",
            "C": "世界百年未有之大变局",
            "D": "中华民族伟大复兴战略全局"
        },
        "correct_answer": "CD",
        "error_count": 0,
        "correct_count": 0
    },
    {
        "question_number": "36",
        "question_type": "多选题",
        "question_text": "2001年7月1日，江泽民在庆祝中国共产党成立八十周年大会上的讲话中全面闸述了“三个代表”重要思想的科学内涵和基本内容，“三个代表”重要思想具体内容为，中国共产党始终代表。",
        "options": {
            "A": "中国先进生产力的发展要求",
            "B": "中国最广大人民的根本利益",
            "C": "中国工人阶级的共同意志",
            "D": "中国先进文化的前进方向"
        },
        "correct_answer": "ABD",
        "error_count": 0,
        "correct_count": 0
    },
    {
        "question_number": "37",
        "question_type": "多选题",
        "question_text": "以胡锦涛同志为主要代表的中国共产 党人领导人民紧紧抓住和用好我国发展的重要战 略机遇期 ，在全面建设小康社会实践中推进( )。",
        "options": {
            "A": "源头创新",
            "B": "制度创新",
            "C": "实践创新",
            "D": "理论创新"
        },
        "correct_answer": "BCD",
        "error_count": 0,
        "correct_count": 0
    },
    {
        "question_number": "38",
        "question_type": "多选题",
        "question_text": "中国共产党百年奋斗的历史经验包括 ()等。",
        "options": {
            "A": "坚持实事求是",
            "B": "坚持人民至上",
            "C": "坚持独立自主",
            "D": "坚持党的领导"
        },
        "correct_answer": "BCD",
        "error_count": 0,
        "correct_count": 0
    },
    {
        "question_number": "39",
        "question_type": "多选题",
        "question_text": "中国特色社会主义进入新时代，意 味着( )。",
        "options": {
            "A": "中国特色社会主义道路、理论、制度、文化不",
            "B": "中华民族迎来了从站起来、富起来到强起来的",
            "C": "科学社会主义在21世纪的中国焕发出强大生机",
            "D": "建党90周年的伟大胜利"
        },
        "correct_answer": "ABC",
        "error_count": 0,
        "correct_count": 0
    }
]